trazelet/__init__.py
trazelet/config.py
trazelet/core/__init__.py
trazelet/core/engine.py
trazelet/core/worker.py
trazelet/db/__init__.py
trazelet/db/config.py
trazelet/db/models.py
trazelet/integrations/__init__.py
trazelet/integrations/django.py
trazelet/integrations/fastapi.py
trazelet/integrations/flask.py
trazelet/tui/analytics.py
trazelet/tui/app.py
trazelet/tui/caching.py
trazelet/tui/services.py
trazelet/utils/helper.py
trazelet/utils/logger_config.py
trazelet-0.1.0.dist-info/licenses/LICENSE
trazelet-0.1.0.dist-info/METADATA
trazelet-0.1.0.dist-info/WHEEL
trazelet-0.1.0.dist-info/entry_points.txt
trazelet-0.1.0.dist-info/top_level.txt
trazelet-0.1.0.dist-info/RECORD
