Metadata-Version: 2.4
Name: trazelet
Version: 0.1.0
Summary: A Lightweight, Zero-Configuration Observability Middleware for Python Backends
Author: Kriz
License-Expression: MIT
Project-URL: Repository, https://github.com/krizzler27/Trazelet
Keywords: API,HTTP,monitoring,performance,tracker,python,backend,analytics
Requires-Python: >=3.11
License-File: LICENSE
Requires-Dist: typer>=0.21.1
Requires-Dist: rich>=14.2.0
Requires-Dist: sqlalchemy>=2.0.45
Requires-Dist: psycopg2>=2.9.11
Requires-Dist: psycopg2-binary>=2.9.11
Provides-Extra: dev
Requires-Dist: fastapi[standard]>=0.128.0; extra == "dev"
Requires-Dist: flask>=3.1.2; extra == "dev"
Requires-Dist: django>=5.2.9; extra == "dev"
Requires-Dist: pytest>=9.0.2; extra == "dev"
Requires-Dist: djangorestframework>=3.16.1; extra == "dev"
Requires-Dist: numpy>=2.4.1; extra == "dev"
Requires-Dist: ruff>=0.14.11; extra == "dev"
Dynamic: license-file
